{
  "user": {
    "username": "Sheila Valencia",
    "profileImage": "https://i.pinimg.com/736x/02/08/12/020812624c380d660646f23ee189724a.jpg",
    "socialLink": "@sheilav"
  },
  "topics": [
    {
      "topic": "first conditional",
      "questions": [
        {
          "question": "If the moon explodes tonight, what will happen to the werewolves?",
          "options": [
            "They will lose their powers.",
            "They would howl louder.",
            "They had hidden already.",
            "They lose their fur."
          ],
          "answer": "They will lose their powers."
        },
        {
          "question": "Choose the correct sentence using the first conditional:",
          "options": [
            "If the aliens land tomorrow, we will invite them for tea.",
            "If aliens landed tomorrow, we invited them for tea.",
            "If the aliens land, we would invite them.",
            "If the aliens had landed, we would have tea."
          ],
          "answer": "If the aliens land tomorrow, we will invite them for tea."
        },
        {
          "question": "Complete the sentence: 'If my cat learns to talk, it _____ all my secrets.'",
          "options": [
            "will reveal",
            "revealed",
            "would reveal",
            "reveals"
          ],
          "answer": "will reveal"
        }
      ]
    }
  ]
}
