{
  "user": {
    "username": "David Enciso",
    "profileImage": "https://i.ytimg.com/vi/NXdOcZvkyK4/maxresdefault.jpg",
    "socialLink": "@cinnamonmint"
  },
  "topics": [
    {
      "topic": "third conditional",
      "questions": [
        {
          "question": "What would have happened if Tom had remembered his umbrella?",
          "options": [
            "He would get wet.",
            "He gets wet.",
            "He would have stayed dry.",
            "He stayed dry."
          ],
          "answer": "He would have stayed dry."
        },
        {
          "question": "Choose the correct third conditional sentence involving an invitation.",
          "options": [
            "If we invited her, she would come.",
            "If we had invited her, she would have come.",
            "If we have invited her, she would come.",
            "If we invite her, she comes."
          ],
          "answer": "If we had invited her, she would have come."
        },
        {
          "question": "Which option correctly completes this third conditional sentence: 'If I had not forgotten the tickets, we _____ the concert.'",
          "options": [
            "would have missed",
            "would have attended",
            "will attend",
            "attend"
          ],
          "answer": "would have attended"
        }
      ]
    }
  ]
}