{
  "user": {
    "username": "Kevin Toro",
    "profileImage": "https://www.shutterstock.com/shutterstock/photos/2478682035/display_1500/stock-vector-bull-head-clip-art-vector-2478682035.jpg",
    "socialLink": "@github.com/KevToro"
  },
  "topics": [
    {
      "topic": "modals_possibility",
      "questions": [
        {
          "question": "Which sentence suggests that someone is *not sure* about where John is now?",
          "options": [
            "John might be in the kitchen.",
            "John is in the kitchen.",
            "John was in the kitchen.",
            "John must be in the kitchen."
          ],
          "answer": "John might be in the kitchen."
        },
        {
          "question": "Complete the sentence: 'It’s cloudy. It _____ rain later.'",
          "options": [
            "might",
            "must",
            "can",
            "should"
          ],
          "answer": "might"
        },
        {
          "question": "Which option shows a possibility that already happened in the past?",
          "options": [
            "She might have forgotten her keys.",
            "She must forget her keys.",
            "She forgets her keys often.",
            "She will forget her keys."
          ],
          "answer": "She might have forgotten her keys."
        }
      ]
      
    }
  ]
}